[{"query":"lawyer, Kwinana, Western Australia, Australia","name":"Tadano Oceania Pty Ltd - WA Branch","site":"https://www.tadano.com.au/?utm_source=google&utm_medium=organic&utm_campaign=gmb&utm_content=wa","type":"Crane dealer","subtypes":"Crane dealer, Construction equipment supplier, Crane service","category":"Crane dealer","phone":"+61 8 9499 6500","full_address":"79 Armstrong Rd, Hope Valley WA 6165","borough":"","street":"79 Armstrong Rd","city":"Hope Valley","postal_code":6165,"state":"Western Australia","us_state":"","country":"Australia","country_code":"AU","latitude":-32.2050548,"longitude":115.7935346,"time_zone":"Australia/Perth","plus_code":"79 Armstrong Rd","rating":4.4,"reviews":5,"reviews_link":"https://search.google.com/local/reviews?placeid=ChIJ-SgPCoWYMioR5B8zhnnBo90&q=lawyer,+Kwinana,+Western+Australia,+Australia&authuser=0&hl=en&gl=AU","reviews_tags":"","reviews_per_score":{"1":0,"2":0,"3":1,"4":1,"5":3},"photos_count":10,"photo":"https://lh5.googleusercontent.com/p/AF1QipOtPvINztax8I0ufoqmgWCPgV4X5p3TGQgodtsI=w800-h500-k-no","street_view":"https://lh5.googleusercontent.com/p/AF1QipOtPvINztax8I0ufoqmgWCPgV4X5p3TGQgodtsI=w1600-h1000-k-no","located_in":"","working_hours":{"Monday":"8:30am–4pm","Tuesday":"8:30am–4pm","Wednesday":"8:30am–4pm","Thursday":"8:30am–4pm","Friday":"8:30am–4pm","Saturday":"Closed","Sunday":"Closed"},"popular_times":"","business_status":"OPERATIONAL","about":{},"range":"","posts":"","logo":"https://lh6.googleusercontent.com/--l8okX9qwkM/AAAAAAAAAAI/AAAAAAAAAAA/CXe6dLJY_wU/s44-p-k-no-ns-nd/photo.jpg","description":"","verified":true,"owner_id":114764926334826870000,"owner_title":"Tadano Oceania Pty Ltd - WA Branch","owner_link":"https://www.google.com/maps/contrib/114764926334826868387","reservation_links":"","booking_appointment_link":"","menu_link":"","order_links":"","location_link":"https://www.google.com/maps/place/Tadano+Oceania+Pty+Ltd+-+WA+Branch/@-32.2050548,115.7935346,14z/data=!4m8!1m2!2m1!1sTadano+Oceania+Pty+Ltd+-+WA+Branch!3m4!1s0x2a3298850a0f28f9:0xdda3c17986331fe4!8m2!3d-32.2050548!4d115.7935346","place_id":"ChIJ-SgPCoWYMioR5B8zhnnBo90","google_id":"0x2a3298850a0f28f9:0xdda3c17986331fe4","cid":-2475922642436940000,"reviews_id":-2475922642436940000,"located_google_id":"","email_1":null,"email_1_full_name":null,"email_1_title":null,"email_2":null,"email_2_full_name":null,"email_2_title":null,"email_3":null,"email_3_full_name":null,"email_3_title":null,"phone_1":1300823266,"phone_2":null,"phone_3":null,"facebook":null,"instagram":null,"linkedin":null,"medium":null,"reddit":null,"skype":null,"snapchat":null,"telegram":null,"whatsapp":null,"twitter":null,"vimeo":null,"youtube":null,"github":null,"crunchbase":null,"title":null,"generator":null,"keywords":null}]