{"averagesByPostCode":{"Average household size":2.3,"Average number of persons per bedroom":0.8,"Median age of persons":54,"Median mortgage repayment ($/monthly)":1830,"Median rent ($/weekly)":340,"Median total family income ($/weekly)":1670,"Median total household income ($/weekly)":1339,"Median total personal income ($/weekly)":680},"houseHoldTypes":{"Other tenure type":38,"Owned outright":542,"Owned with a mortgage":360,"Rented: Community housing provider":4,"Rented: Landlord type not stated":0,"Rented: Other landlord type":39,"Rented: Person not in same household":42,"Rented: Real estate agent":163,"Rented: State or territory housing authority":0,"Rented: Total":252,"Tenure type not stated":11,"Total":1199},"populationByPostCode":{"0-4 years / Females":66,"0-4 years / Males":72,"0-4 years / Persons":135,"10-14 years / Females":66,"10-14 years / Males":80,"10-14 years / Persons":140,"100 years and over / Females":0,"100 years and over / Males":0,"100 years and over / Persons":0,"15-19 years / Females":65,"15-19 years / Males":58,"15-19 years / Persons":125,"20-24 years / Females":50,"20-24 years / Males":57,"20-24 years / Persons":111,"25-29 years / Females":58,"25-29 years / Males":44,"25-29 years / Persons":95,"30-34 years / Females":80,"30-34 years / Males":57,"30-34 years / Persons":133,"35-39 years / Females":71,"35-39 years / Males":75,"35-39 years / Persons":145,"40-44 years / Females":74,"40-44 years / Males":80,"40-44 years / Persons":154,"45-49 years / Females":72,"45-49 years / Males":74,"45-49 years / Persons":147,"5-9 years / Females":60,"5-9 years / Males":82,"5-9 years / Persons":136,"50-54 years / Females":90,"50-54 years / Males":88,"50-54 years / Persons":175,"55-59 years / Females":110,"55-59 years / Males":108,"55-59 years / Persons":219,"60-64 years / Females":158,"60-64 years / Males":104,"60-64 years / Persons":262,"65-69 years / Females":133,"65-69 years / Males":152,"65-69 years / Persons":282,"70-74 years / Females":139,"70-74 years / Males":134,"70-74 years / Persons":275,"75-79 years / Females":83,"75-79 years / Males":111,"75-79 years / Persons":197,"80-84 years / Females":56,"80-84 years / Males":51,"80-84 years / Persons":108,"85-89 years / Females":29,"85-89 years / Males":25,"85-89 years / Persons":55,"90-94 years / Females":12,"90-94 years / Males":10,"90-94 years / Persons":21,"95-99 years / Females":0,"95-99 years / Males":0,"95-99 years / Persons":4},"maritalStatus":{"Divorced":305,"Married":1307,"Never married":650,"Separated":97,"Total":2501,"Widowed":150}}