{"populationByPostCode":{"0-4 years / Females":582,"0-4 years / Males":605,"0-4 years / Persons":1190,"10-14 years / Females":781,"10-14 years / Males":818,"10-14 years / Persons":1601,"100 years and over / Females":8,"100 years and over / Males":0,"100 years and over / Persons":6,"15-19 years / Females":678,"15-19 years / Males":762,"15-19 years / Persons":1436,"20-24 years / Females":619,"20-24 years / Males":649,"20-24 years / Persons":1271,"25-29 years / Females":670,"25-29 years / Males":651,"25-29 years / Persons":1323,"30-34 years / Females":612,"30-34 years / Males":654,"30-34 years / Persons":1265,"35-39 years / Females":641,"35-39 years / Males":652,"35-39 years / Persons":1293,"40-44 years / Females":681,"40-44 years / Males":587,"40-44 years / Persons":1269,"45-49 years / Females":729,"45-49 years / Males":697,"45-49 years / Persons":1428,"5-9 years / Females":700,"5-9 years / Males":780,"5-9 years / Persons":1483,"50-54 years / Females":783,"50-54 years / Males":764,"50-54 years / Persons":1548,"55-59 years / Females":908,"55-59 years / Males":891,"55-59 years / Persons":1799,"60-64 years / Females":976,"60-64 years / Males":886,"60-64 years / Persons":1862,"65-69 years / Females":958,"65-69 years / Males":950,"65-69 years / Persons":1909,"70-74 years / Females":955,"70-74 years / Males":938,"70-74 years / Persons":1893,"75-79 years / Females":683,"75-79 years / Males":676,"75-79 years / Persons":1357,"80-84 years / Females":432,"80-84 years / Males":411,"80-84 years / Persons":839,"85-89 years / Females":248,"85-89 years / Males":200,"85-89 years / Persons":443,"90-94 years / Females":111,"90-94 years / Males":76,"90-94 years / Persons":193,"95-99 years / Females":13,"95-99 years / Males":17,"95-99 years / Persons":31},"averagesByPostCode":{"Average household size":2.4,"Average number of persons per bedroom":0.7,"Median age of persons":47,"Median mortgage repayment ($/monthly)":1560,"Median rent ($/weekly)":330,"Median total family income ($/weekly)":1482,"Median total household income ($/weekly)":1254,"Median total personal income ($/weekly)":631},"maritalStatus":{"Divorced":2357,"Married":9705,"Never married":6894,"Separated":859,"Total":21181,"Widowed":1364},"houseHoldTypes":{"Other tenure type":394,"Owned outright":3695,"Owned with a mortgage":2831,"Rented: Community housing provider":163,"Rented: Landlord type not stated":16,"Rented: Other landlord type":192,"Rented: Person not in same household":408,"Rented: Real estate agent":1535,"Rented: State or territory housing authority":456,"Rented: Total":2769,"Tenure type not stated":160,"Total":9852}}