{"houseHoldTypes":{"Other tenure type":83,"Owned outright":1623,"Owned with a mortgage":1344,"Rented: Community housing provider":31,"Rented: Landlord type not stated":13,"Rented: Other landlord type":39,"Rented: Person not in same household":512,"Rented: Real estate agent":611,"Rented: State or territory housing authority":19,"Rented: Total":1221,"Tenure type not stated":86,"Total":4356},"averagesByPostCode":{"Average household size":2.4,"Average number of persons per bedroom":0.8,"Median age of persons":44,"Median mortgage repayment ($/monthly)":1898,"Median rent ($/weekly)":480,"Median total family income ($/weekly)":1731,"Median total household income ($/weekly)":1442,"Median total personal income ($/weekly)":708},"maritalStatus":{"Divorced":1373,"Married":3422,"Never married":4187,"Separated":342,"Total":9728,"Widowed":406},"populationByPostCode":{"0-4 years / Females":326,"0-4 years / Males":275,"0-4 years / Persons":603,"10-14 years / Females":345,"10-14 years / Males":309,"10-14 years / Persons":656,"100 years and over / Females":0,"100 years and over / Males":0,"100 years and over / Persons":0,"15-19 years / Females":290,"15-19 years / Males":270,"15-19 years / Persons":563,"20-24 years / Females":262,"20-24 years / Males":221,"20-24 years / Persons":479,"25-29 years / Females":314,"25-29 years / Males":286,"25-29 years / Persons":600,"30-34 years / Females":415,"30-34 years / Males":344,"30-34 years / Persons":758,"35-39 years / Females":437,"35-39 years / Males":376,"35-39 years / Persons":808,"40-44 years / Females":405,"40-44 years / Males":374,"40-44 years / Persons":777,"45-49 years / Females":492,"45-49 years / Males":396,"45-49 years / Persons":894,"5-9 years / Females":300,"5-9 years / Males":329,"5-9 years / Persons":628,"50-54 years / Females":455,"50-54 years / Males":372,"50-54 years / Persons":825,"55-59 years / Females":465,"55-59 years / Males":390,"55-59 years / Persons":858,"60-64 years / Females":497,"60-64 years / Males":424,"60-64 years / Persons":924,"65-69 years / Females":413,"65-69 years / Males":440,"65-69 years / Persons":858,"70-74 years / Females":295,"70-74 years / Males":330,"70-74 years / Persons":622,"75-79 years / Females":185,"75-79 years / Males":184,"75-79 years / Persons":368,"80-84 years / Females":115,"80-84 years / Males":96,"80-84 years / Persons":209,"85-89 years / Females":67,"85-89 years / Males":47,"85-89 years / Persons":116,"90-94 years / Females":35,"90-94 years / Males":23,"90-94 years / Persons":62,"95-99 years / Females":10,"95-99 years / Males":4,"95-99 years / Persons":13}}