{"averagesByPostCode":{"Average household size":2.6,"Average number of persons per bedroom":0.8,"Median age of persons":40,"Median mortgage repayment ($/monthly)":1343,"Median rent ($/weekly)":260,"Median total family income ($/weekly)":1935,"Median total household income ($/weekly)":1606,"Median total personal income ($/weekly)":763},"maritalStatus":{"Divorced":347,"Married":2495,"Never married":1555,"Separated":156,"Total":4819,"Widowed":271},"populationByPostCode":{"0-4 years / Females":170,"0-4 years / Males":172,"0-4 years / Persons":341,"10-14 years / Females":200,"10-14 years / Males":242,"10-14 years / Persons":446,"100 years and over / Females":0,"100 years and over / Males":0,"100 years and over / Persons":0,"15-19 years / Females":191,"15-19 years / Males":210,"15-19 years / Persons":399,"20-24 years / Females":161,"20-24 years / Males":164,"20-24 years / Persons":330,"25-29 years / Females":181,"25-29 years / Males":190,"25-29 years / Persons":376,"30-34 years / Females":168,"30-34 years / Males":186,"30-34 years / Persons":357,"35-39 years / Females":178,"35-39 years / Males":178,"35-39 years / Persons":353,"40-44 years / Females":175,"40-44 years / Males":171,"40-44 years / Persons":351,"45-49 years / Females":204,"45-49 years / Males":187,"45-49 years / Persons":386,"5-9 years / Females":175,"5-9 years / Males":195,"5-9 years / Persons":366,"50-54 years / Females":237,"50-54 years / Males":220,"50-54 years / Persons":458,"55-59 years / Females":170,"55-59 years / Males":181,"55-59 years / Persons":344,"60-64 years / Females":199,"60-64 years / Males":195,"60-64 years / Persons":393,"65-69 years / Females":156,"65-69 years / Males":173,"65-69 years / Persons":329,"70-74 years / Females":148,"70-74 years / Males":160,"70-74 years / Persons":310,"75-79 years / Females":101,"75-79 years / Males":114,"75-79 years / Persons":211,"80-84 years / Females":76,"80-84 years / Males":62,"80-84 years / Persons":137,"85-89 years / Females":47,"85-89 years / Males":30,"85-89 years / Persons":81,"90-94 years / Females":15,"90-94 years / Males":6,"90-94 years / Persons":16,"95-99 years / Females":8,"95-99 years / Males":0,"95-99 years / Persons":8},"houseHoldTypes":{"Other tenure type":39,"Owned outright":762,"Owned with a mortgage":855,"Rented: Community housing provider":9,"Rented: Landlord type not stated":11,"Rented: Other landlord type":29,"Rented: Person not in same household":123,"Rented: Real estate agent":178,"Rented: State or territory housing authority":8,"Rented: Total":351,"Tenure type not stated":51,"Total":2058}}