{"averagesByPostCode":{"Average household size":2.3,"Average number of persons per bedroom":0.7,"Median age of persons":47,"Median mortgage repayment ($/monthly)":1600,"Median rent ($/weekly)":331,"Median total family income ($/weekly)":1790,"Median total household income ($/weekly)":1360,"Median total personal income ($/weekly)":756},"houseHoldTypes":{"Other tenure type":68,"Owned outright":988,"Owned with a mortgage":701,"Rented: Community housing provider":3,"Rented: Landlord type not stated":0,"Rented: Other landlord type":19,"Rented: Person not in same household":107,"Rented: Real estate agent":279,"Rented: State or territory housing authority":51,"Rented: Total":466,"Tenure type not stated":40,"Total":2266},"maritalStatus":{"Divorced":468,"Married":2382,"Never married":1403,"Separated":153,"Total":4758,"Widowed":347},"populationByPostCode":{"0-4 years / Females":134,"0-4 years / Males":125,"0-4 years / Persons":265,"10-14 years / Females":196,"10-14 years / Males":207,"10-14 years / Persons":396,"100 years and over / Females":3,"100 years and over / Males":0,"100 years and over / Persons":3,"15-19 years / Females":133,"15-19 years / Males":130,"15-19 years / Persons":262,"20-24 years / Females":75,"20-24 years / Males":106,"20-24 years / Persons":185,"25-29 years / Females":152,"25-29 years / Males":134,"25-29 years / Persons":284,"30-34 years / Females":133,"30-34 years / Males":136,"30-34 years / Persons":266,"35-39 years / Females":180,"35-39 years / Males":163,"35-39 years / Persons":346,"40-44 years / Females":189,"40-44 years / Males":169,"40-44 years / Persons":361,"45-49 years / Females":165,"45-49 years / Males":166,"45-49 years / Persons":326,"5-9 years / Females":186,"5-9 years / Males":200,"5-9 years / Persons":388,"50-54 years / Females":179,"50-54 years / Males":162,"50-54 years / Persons":341,"55-59 years / Females":204,"55-59 years / Males":183,"55-59 years / Persons":379,"60-64 years / Females":282,"60-64 years / Males":232,"60-64 years / Persons":507,"65-69 years / Females":222,"65-69 years / Males":222,"65-69 years / Persons":451,"70-74 years / Females":208,"70-74 years / Males":183,"70-74 years / Persons":390,"75-79 years / Females":152,"75-79 years / Males":130,"75-79 years / Persons":288,"80-84 years / Females":104,"80-84 years / Males":91,"80-84 years / Persons":200,"85-89 years / Females":71,"85-89 years / Males":28,"85-89 years / Persons":101,"90-94 years / Females":30,"90-94 years / Males":28,"90-94 years / Persons":60,"95-99 years / Females":12,"95-99 years / Males":3,"95-99 years / Persons":14}}