{"populationByPostCode":{"0-4 years / Females":150,"0-4 years / Males":206,"0-4 years / Persons":355,"10-14 years / Females":217,"10-14 years / Males":248,"10-14 years / Persons":463,"100 years and over / Females":4,"100 years and over / Males":0,"100 years and over / Persons":5,"15-19 years / Females":203,"15-19 years / Males":224,"15-19 years / Persons":424,"20-24 years / Females":139,"20-24 years / Males":165,"20-24 years / Persons":307,"25-29 years / Females":179,"25-29 years / Males":137,"25-29 years / Persons":311,"30-34 years / Females":200,"30-34 years / Males":164,"30-34 years / Persons":359,"35-39 years / Females":211,"35-39 years / Males":192,"35-39 years / Persons":405,"40-44 years / Females":192,"40-44 years / Males":191,"40-44 years / Persons":388,"45-49 years / Females":222,"45-49 years / Males":229,"45-49 years / Persons":446,"5-9 years / Females":214,"5-9 years / Males":220,"5-9 years / Persons":437,"50-54 years / Females":292,"50-54 years / Males":238,"50-54 years / Persons":527,"55-59 years / Females":324,"55-59 years / Males":299,"55-59 years / Persons":626,"60-64 years / Females":374,"60-64 years / Males":341,"60-64 years / Persons":715,"65-69 years / Females":443,"65-69 years / Males":435,"65-69 years / Persons":874,"70-74 years / Females":402,"70-74 years / Males":432,"70-74 years / Persons":832,"75-79 years / Females":288,"75-79 years / Males":316,"75-79 years / Persons":603,"80-84 years / Females":174,"80-84 years / Males":172,"80-84 years / Persons":349,"85-89 years / Females":107,"85-89 years / Males":75,"85-89 years / Persons":180,"90-94 years / Females":59,"90-94 years / Males":33,"90-94 years / Persons":91,"95-99 years / Females":9,"95-99 years / Males":9,"95-99 years / Persons":18},"maritalStatus":{"Divorced":843,"Married":3550,"Never married":2106,"Separated":351,"Total":7456,"Widowed":612},"averagesByPostCode":{"Average household size":2.2,"Average number of persons per bedroom":0.7,"Median age of persons":54,"Median mortgage repayment ($/monthly)":1300,"Median rent ($/weekly)":260,"Median total family income ($/weekly)":1300,"Median total household income ($/weekly)":964,"Median total personal income ($/weekly)":549},"houseHoldTypes":{"Other tenure type":57,"Owned outright":1723,"Owned with a mortgage":836,"Rented: Community housing provider":38,"Rented: Landlord type not stated":7,"Rented: Other landlord type":48,"Rented: Person not in same household":184,"Rented: Real estate agent":417,"Rented: State or territory housing authority":132,"Rented: Total":820,"Tenure type not stated":96,"Total":3521}}