{"averagesByPostCode":{"Average household size":2.4,"Average number of persons per bedroom":0.8,"Median age of persons":41,"Median mortgage repayment ($/monthly)":2105,"Median rent ($/weekly)":350,"Median total family income ($/weekly)":2724,"Median total household income ($/weekly)":2020,"Median total personal income ($/weekly)":1003},"houseHoldTypes":{"Other tenure type":74,"Owned outright":1504,"Owned with a mortgage":1205,"Rented: Community housing provider":26,"Rented: Landlord type not stated":4,"Rented: Other landlord type":20,"Rented: Person not in same household":335,"Rented: Real estate agent":820,"Rented: State or territory housing authority":54,"Rented: Total":1263,"Tenure type not stated":27,"Total":4076},"maritalStatus":{"Divorced":771,"Married":3904,"Never married":3261,"Separated":197,"Total":8563,"Widowed":428},"populationByPostCode":{"0-4 years / Females":235,"0-4 years / Males":257,"0-4 years / Persons":487,"10-14 years / Females":290,"10-14 years / Males":289,"10-14 years / Persons":577,"100 years and over / Females":0,"100 years and over / Males":0,"100 years and over / Persons":0,"15-19 years / Females":269,"15-19 years / Males":245,"15-19 years / Persons":514,"20-24 years / Females":359,"20-24 years / Males":344,"20-24 years / Persons":707,"25-29 years / Females":357,"25-29 years / Males":338,"25-29 years / Persons":695,"30-34 years / Females":347,"30-34 years / Males":336,"30-34 years / Persons":687,"35-39 years / Females":370,"35-39 years / Males":307,"35-39 years / Persons":679,"40-44 years / Females":359,"40-44 years / Males":312,"40-44 years / Persons":669,"45-49 years / Females":325,"45-49 years / Males":315,"45-49 years / Persons":642,"5-9 years / Females":244,"5-9 years / Males":272,"5-9 years / Persons":515,"50-54 years / Females":363,"50-54 years / Males":328,"50-54 years / Persons":689,"55-59 years / Females":328,"55-59 years / Males":295,"55-59 years / Persons":625,"60-64 years / Females":359,"60-64 years / Males":313,"60-64 years / Persons":670,"65-69 years / Females":333,"65-69 years / Males":271,"65-69 years / Persons":600,"70-74 years / Females":294,"70-74 years / Males":247,"70-74 years / Persons":535,"75-79 years / Females":177,"75-79 years / Males":178,"75-79 years / Persons":354,"80-84 years / Females":128,"80-84 years / Males":94,"80-84 years / Persons":216,"85-89 years / Females":87,"85-89 years / Males":52,"85-89 years / Persons":139,"90-94 years / Females":84,"90-94 years / Males":33,"90-94 years / Persons":114,"95-99 years / Females":20,"95-99 years / Males":4,"95-99 years / Persons":23}}