{"averagesByPostCode":{"Average household size":1.8,"Average number of persons per bedroom":1,"Median age of persons":33,"Median mortgage repayment ($/monthly)":1733,"Median rent ($/weekly)":380,"Median total family income ($/weekly)":2525,"Median total household income ($/weekly)":1843,"Median total personal income ($/weekly)":1130},"maritalStatus":{"Divorced":310,"Married":858,"Never married":2027,"Separated":112,"Total":3372,"Widowed":64},"houseHoldTypes":{"Other tenure type":28,"Owned outright":252,"Owned with a mortgage":388,"Rented: Community housing provider":22,"Rented: Landlord type not stated":3,"Rented: Other landlord type":34,"Rented: Person not in same household":197,"Rented: Real estate agent":714,"Rented: State or territory housing authority":74,"Rented: Total":1042,"Tenure type not stated":16,"Total":1724},"populationByPostCode":{"0-4 years / Females":55,"0-4 years / Males":62,"0-4 years / Persons":116,"10-14 years / Females":36,"10-14 years / Males":34,"10-14 years / Persons":74,"100 years and over / Females":0,"100 years and over / Males":0,"100 years and over / Persons":0,"15-19 years / Females":40,"15-19 years / Males":29,"15-19 years / Persons":67,"20-24 years / Females":198,"20-24 years / Males":152,"20-24 years / Persons":357,"25-29 years / Females":313,"25-29 years / Males":354,"25-29 years / Persons":668,"30-34 years / Females":329,"30-34 years / Males":342,"30-34 years / Persons":672,"35-39 years / Females":170,"35-39 years / Males":253,"35-39 years / Persons":421,"40-44 years / Females":96,"40-44 years / Males":129,"40-44 years / Persons":226,"45-49 years / Females":83,"45-49 years / Males":105,"45-49 years / Persons":192,"5-9 years / Females":45,"5-9 years / Males":47,"5-9 years / Persons":91,"50-54 years / Females":69,"50-54 years / Males":106,"50-54 years / Persons":172,"55-59 years / Females":59,"55-59 years / Males":80,"55-59 years / Persons":142,"60-64 years / Females":81,"60-64 years / Males":82,"60-64 years / Persons":161,"65-69 years / Females":60,"65-69 years / Males":55,"65-69 years / Persons":114,"70-74 years / Females":41,"70-74 years / Males":52,"70-74 years / Persons":94,"75-79 years / Females":9,"75-79 years / Males":33,"75-79 years / Persons":39,"80-84 years / Females":25,"80-84 years / Males":13,"80-84 years / Persons":37,"85-89 years / Females":9,"85-89 years / Males":3,"85-89 years / Persons":9,"90-94 years / Females":4,"90-94 years / Males":4,"90-94 years / Persons":9,"95-99 years / Females":0,"95-99 years / Males":0,"95-99 years / Persons":3}}