{"averagesByPostCode":{"Average household size":2.6,"Average number of persons per bedroom":0.7,"Median age of persons":47,"Median mortgage repayment ($/monthly)":2139,"Median rent ($/weekly)":360,"Median total family income ($/weekly)":2367,"Median total household income ($/weekly)":1944,"Median total personal income ($/weekly)":811},"populationByPostCode":{"0-4 years / Females":444,"0-4 years / Males":454,"0-4 years / Persons":901,"10-14 years / Females":805,"10-14 years / Males":899,"10-14 years / Persons":1707,"100 years and over / Females":5,"100 years and over / Males":0,"100 years and over / Persons":3,"15-19 years / Females":698,"15-19 years / Males":769,"15-19 years / Persons":1465,"20-24 years / Females":488,"20-24 years / Males":607,"20-24 years / Persons":1094,"25-29 years / Females":351,"25-29 years / Males":353,"25-29 years / Persons":705,"30-34 years / Females":441,"30-34 years / Males":396,"30-34 years / Persons":840,"35-39 years / Females":614,"35-39 years / Males":488,"35-39 years / Persons":1107,"40-44 years / Females":705,"40-44 years / Males":665,"40-44 years / Persons":1369,"45-49 years / Females":790,"45-49 years / Males":767,"45-49 years / Persons":1556,"5-9 years / Females":653,"5-9 years / Males":678,"5-9 years / Persons":1329,"50-54 years / Females":847,"50-54 years / Males":821,"50-54 years / Persons":1671,"55-59 years / Females":810,"55-59 years / Males":796,"55-59 years / Persons":1608,"60-64 years / Females":725,"60-64 years / Males":669,"60-64 years / Persons":1395,"65-69 years / Females":732,"65-69 years / Males":677,"65-69 years / Persons":1409,"70-74 years / Females":802,"70-74 years / Males":756,"70-74 years / Persons":1560,"75-79 years / Females":572,"75-79 years / Males":560,"75-79 years / Persons":1126,"80-84 years / Females":416,"80-84 years / Males":371,"80-84 years / Persons":792,"85-89 years / Females":267,"85-89 years / Males":196,"85-89 years / Persons":459,"90-94 years / Females":107,"90-94 years / Males":65,"90-94 years / Persons":164,"95-99 years / Females":32,"95-99 years / Males":19,"95-99 years / Persons":46},"houseHoldTypes":{"Other tenure type":107,"Owned outright":3718,"Owned with a mortgage":3190,"Rented: Community housing provider":41,"Rented: Landlord type not stated":12,"Rented: Other landlord type":23,"Rented: Person not in same household":383,"Rented: Real estate agent":430,"Rented: State or territory housing authority":53,"Rented: Total":931,"Tenure type not stated":90,"Total":8039},"maritalStatus":{"Divorced":1486,"Married":10392,"Never married":4917,"Separated":493,"Total":18368,"Widowed":1085}}