{"averagesByPostCode":{"Average household size":2.3,"Average number of persons per bedroom":0.9,"Median age of persons":37,"Median mortgage repayment ($/monthly)":714,"Median rent ($/weekly)":163,"Median total family income ($/weekly)":1671,"Median total household income ($/weekly)":1446,"Median total personal income ($/weekly)":1092},"houseHoldTypes":{"Other tenure type":17,"Owned outright":59,"Owned with a mortgage":27,"Rented: Community housing provider":3,"Rented: Landlord type not stated":0,"Rented: Other landlord type":24,"Rented: Person not in same household":20,"Rented: Real estate agent":0,"Rented: State or territory housing authority":23,"Rented: Total":76,"Tenure type not stated":19,"Total":199},"maritalStatus":{"Divorced":56,"Married":263,"Never married":349,"Separated":36,"Total":732,"Widowed":21},"populationByPostCode":{"0-4 years / Females":21,"0-4 years / Males":18,"0-4 years / Persons":38,"10-14 years / Females":14,"10-14 years / Males":18,"10-14 years / Persons":31,"100 years and over / Females":0,"100 years and over / Males":0,"100 years and over / Persons":0,"15-19 years / Females":21,"15-19 years / Males":16,"15-19 years / Persons":32,"20-24 years / Females":20,"20-24 years / Males":33,"20-24 years / Persons":55,"25-29 years / Females":25,"25-29 years / Males":73,"25-29 years / Persons":93,"30-34 years / Females":28,"30-34 years / Males":68,"30-34 years / Persons":97,"35-39 years / Females":28,"35-39 years / Males":43,"35-39 years / Persons":71,"40-44 years / Females":19,"40-44 years / Males":36,"40-44 years / Persons":57,"45-49 years / Females":24,"45-49 years / Males":34,"45-49 years / Persons":57,"5-9 years / Females":20,"5-9 years / Males":19,"5-9 years / Persons":36,"50-54 years / Females":27,"50-54 years / Males":43,"50-54 years / Persons":67,"55-59 years / Females":27,"55-59 years / Males":33,"55-59 years / Persons":62,"60-64 years / Females":21,"60-64 years / Males":35,"60-64 years / Persons":56,"65-69 years / Females":17,"65-69 years / Males":21,"65-69 years / Persons":37,"70-74 years / Females":11,"70-74 years / Males":11,"70-74 years / Persons":26,"75-79 years / Females":6,"75-79 years / Males":8,"75-79 years / Persons":17,"80-84 years / Females":6,"80-84 years / Males":3,"80-84 years / Persons":6,"85-89 years / Females":0,"85-89 years / Males":0,"85-89 years / Persons":0,"90-94 years / Females":0,"90-94 years / Males":3,"90-94 years / Persons":5,"95-99 years / Females":0,"95-99 years / Males":0,"95-99 years / Persons":0}}