{"populationByPostCode":{"0-4 years / Females":52,"0-4 years / Males":62,"0-4 years / Persons":109,"10-14 years / Females":60,"10-14 years / Males":55,"10-14 years / Persons":113,"100 years and over / Females":0,"100 years and over / Males":0,"100 years and over / Persons":0,"15-19 years / Females":53,"15-19 years / Males":47,"15-19 years / Persons":103,"20-24 years / Females":48,"20-24 years / Males":58,"20-24 years / Persons":104,"25-29 years / Females":51,"25-29 years / Males":46,"25-29 years / Persons":98,"30-34 years / Females":48,"30-34 years / Males":47,"30-34 years / Persons":96,"35-39 years / Females":57,"35-39 years / Males":85,"35-39 years / Persons":142,"40-44 years / Females":45,"40-44 years / Males":45,"40-44 years / Persons":90,"45-49 years / Females":39,"45-49 years / Males":58,"45-49 years / Persons":98,"5-9 years / Females":64,"5-9 years / Males":51,"5-9 years / Persons":119,"50-54 years / Females":49,"50-54 years / Males":57,"50-54 years / Persons":106,"55-59 years / Females":54,"55-59 years / Males":37,"55-59 years / Persons":91,"60-64 years / Females":37,"60-64 years / Males":47,"60-64 years / Persons":80,"65-69 years / Females":17,"65-69 years / Males":39,"65-69 years / Persons":59,"70-74 years / Females":12,"70-74 years / Males":21,"70-74 years / Persons":32,"75-79 years / Females":16,"75-79 years / Males":11,"75-79 years / Persons":28,"80-84 years / Females":0,"80-84 years / Males":4,"80-84 years / Persons":11,"85-89 years / Females":0,"85-89 years / Males":0,"85-89 years / Persons":0,"90-94 years / Females":4,"90-94 years / Males":0,"90-94 years / Persons":4,"95-99 years / Females":0,"95-99 years / Males":0,"95-99 years / Persons":0},"averagesByPostCode":{"Average household size":3,"Average number of persons per bedroom":1.1,"Median age of persons":34,"Median mortgage repayment ($/monthly)":1224,"Median rent ($/weekly)":123,"Median total family income ($/weekly)":951,"Median total household income ($/weekly)":1165,"Median total personal income ($/weekly)":460},"houseHoldTypes":{"Other tenure type":31,"Owned outright":68,"Owned with a mortgage":20,"Rented: Community housing provider":106,"Rented: Landlord type not stated":0,"Rented: Other landlord type":31,"Rented: Person not in same household":37,"Rented: Real estate agent":5,"Rented: State or territory housing authority":71,"Rented: Total":248,"Tenure type not stated":23,"Total":389},"maritalStatus":{"Divorced":54,"Married":236,"Never married":767,"Separated":38,"Total":1134,"Widowed":45}}