{"houseHoldTypes":{"Other tenure type":98,"Owned outright":2077,"Owned with a mortgage":2098,"Rented: Community housing provider":126,"Rented: Landlord type not stated":23,"Rented: Other landlord type":108,"Rented: Person not in same household":677,"Rented: Real estate agent":1270,"Rented: State or territory housing authority":726,"Rented: Total":2928,"Tenure type not stated":144,"Total":7345},"populationByPostCode":{"0-4 years / Females":493,"0-4 years / Males":495,"0-4 years / Persons":987,"10-14 years / Females":465,"10-14 years / Males":494,"10-14 years / Persons":957,"100 years and over / Females":8,"100 years and over / Males":0,"100 years and over / Persons":4,"15-19 years / Females":427,"15-19 years / Males":446,"15-19 years / Persons":876,"20-24 years / Females":579,"20-24 years / Males":544,"20-24 years / Persons":1120,"25-29 years / Females":885,"25-29 years / Males":1017,"25-29 years / Persons":1904,"30-34 years / Females":855,"30-34 years / Males":961,"30-34 years / Persons":1819,"35-39 years / Females":629,"35-39 years / Males":650,"35-39 years / Persons":1285,"40-44 years / Females":505,"40-44 years / Males":486,"40-44 years / Persons":997,"45-49 years / Females":481,"45-49 years / Males":463,"45-49 years / Persons":943,"5-9 years / Females":440,"5-9 years / Males":447,"5-9 years / Persons":888,"50-54 years / Females":504,"50-54 years / Males":472,"50-54 years / Persons":974,"55-59 years / Females":519,"55-59 years / Males":514,"55-59 years / Persons":1035,"60-64 years / Females":531,"60-64 years / Males":525,"60-64 years / Persons":1053,"65-69 years / Females":528,"65-69 years / Males":424,"65-69 years / Persons":949,"70-74 years / Females":460,"70-74 years / Males":362,"70-74 years / Persons":819,"75-79 years / Females":406,"75-79 years / Males":270,"75-79 years / Persons":674,"80-84 years / Females":287,"80-84 years / Males":222,"80-84 years / Persons":514,"85-89 years / Females":203,"85-89 years / Males":132,"85-89 years / Persons":337,"90-94 years / Females":116,"90-94 years / Males":69,"90-94 years / Persons":185,"95-99 years / Females":42,"95-99 years / Males":19,"95-99 years / Persons":60},"maritalStatus":{"Divorced":1670,"Married":6002,"Never married":6210,"Separated":528,"Total":15544,"Widowed":1127},"averagesByPostCode":{"Average household size":2.4,"Average number of persons per bedroom":0.9,"Median age of persons":37,"Median mortgage repayment ($/monthly)":1300,"Median rent ($/weekly)":320,"Median total family income ($/weekly)":1503,"Median total household income ($/weekly)":1222,"Median total personal income ($/weekly)":647}}